Workbook

Sheet Settings
A1: ARB Corporation (ASX: ARB) — Value Analysis — Settings
A3: COMPANY DETAILS
A4: Company Name | B4: ARB Corporation
A5: ASX Ticker | B5: ARB
A6: Business | B6: 4WD accessories manufacturer & retailer — Aus domestic + export
A7: VALUATION ASSUMPTIONS
A8: Buy Multiple (P/E) | B8: 20 | C8: SLOW TO BUY: price < TTM EPS × 20 ÷ 100
A9: Sell Multiple (P/E) | B9: 35 | C9: EVEN SLOWER TO SELL: price > TTM EPS × 35 ÷ 100
A10: Required Rate of Return (RRoR) | B10: 0.03 | C10: Min dividend yield you require (3%) — drives Div/RRoR line
A14: ANALYSIS PERIOD
A15: From (approx.) | B15: Jan 2016
A16: To (approx.) | B16: Latest available
A17: HOW TO REFRESH SHARE PRICE DATA
A18: 1. Go to marketindex.com.au/asx/arb — export daily CSV (Date as YYYYMMDD)
A19: 2. Ensure CSV columns: Date, Open, High, Low, Close, Volume
A20: 3. In PriceData sheet: paste Date → col A, Close → col B from row 3 onwards
A21: 4. PriceData uses WEEKLY Friday close (resampled). Paste daily — agent resamples.
A22: 5. Chart updates automatically.
A23: 6. Microsoft 365: =STOCKHISTORY("ARB.AX",DATE(2016,1,1),TODAY(),0,1,0,1)

Sheet EarningsData
A1: ARB Corporation (ASX: ARB) — Half-Year Earnings & Dividend Data
A2: Ann. Date | B2: Period | C2: Half EPS (AUD ¢) | D2: TTM EPS (AUD ¢) | E2: Half Div (AUD ¢) | F2: TTM Div (AUD ¢) | G2: Value Buy (20× E) | H2: Value Sell (35× E) | I2: Div / RRoR (÷RRoR÷100) | J2: Notes
A3: 42419 | B3: H1 FY2016 | C3: 27.5 | D3: 55 | E3: 13 | F3: 26 | G3: =D3*Settings!$B$8/100 | H3: =D3*Settings!$B$9/100 | I3: =F3/Settings!$B$10/100
A4: 42601 | B4: FY2016 | C4: 34.5 | D4: 62 | E4: 16 | F4: 29 | G4: =D4*Settings!$B$8/100 | H4: =D4*Settings!$B$9/100 | I4: =F4/Settings!$B$10/100
A5: 42783 | B5: H1 FY2017 | C5: 34 | D5: 65 | E5: 16 | F5: 30.5 | G5: =D5*Settings!$B$8/100 | H5: =D5*Settings!$B$9/100 | I5: =F5/Settings!$B$10/100
A6: 42965 | B6: FY2017 | C6: 40.5 | D6: 73 | E6: 18.8 | F6: 34 | G6: =D6*Settings!$B$8/100 | H6: =D6*Settings!$B$9/100 | I6: =F6/Settings!$B$10/100
A7: 43147 | B7: H1 FY2018 | C7: 41 | D7: 77.5 | E7: 19 | F7: 36 | G7: =D7*Settings!$B$8/100 | H7: =D7*Settings!$B$9/100 | I7: =F7/Settings!$B$10/100
A8: 43329 | B8: FY2018 | C8: 48.2 | D8: 87 | E8: 22 | F8: 40 | G8: =D8*Settings!$B$8/100 | H8: =D8*Settings!$B$9/100 | I8: =F8/Settings!$B$10/100
A9: 43511 | B9: H1 FY2019 | C9: 45 | D9: 88.5 | E9: 21.5 | F9: 41.5 | G9: =D9*Settings!$B$8/100 | H9: =D9*Settings!$B$9/100 | I9: =F9/Settings!$B$10/100
A10: 43693 | B10: FY2019 | C10: 50.8 | D10: 95 | E10: 23.2 | F10: 44 | G10: =D10*Settings!$B$8/100 | H10: =D10*Settings!$B$9/100 | I10: =F10/Settings!$B$10/100
A11: 43875 | B11: H1 FY2020 | C11: 44.5 | D11: 92 | E11: 21 | F11: 43 | G11: =D11*Settings!$B$8/100 | H11: =D11*Settings!$B$9/100 | I11: =F11/Settings!$B$10/100 | J11: COVID uncertainty
A12: 44064 | B12: FY2020 | C12: 40 | D12: 86 | E12: 18.5 | F12: 40 | G12: =D12*Settings!$B$8/100 | H12: =D12*Settings!$B$9/100 | I12: =F12/Settings!$B$10/100 | J12: COVID year
A13: 44246 | B13: H1 FY2021 | C13: 67 | D13: 110 | E13: 26 | F13: 46 | G13: =D13*Settings!$B$8/100 | H13: =D13*Settings!$B$9/100 | I13: =F13/Settings!$B$10/100 | J13: 4WD demand surge
A14: 44428 | B14: FY2021 | C14: 95 | D14: 150 | E14: 31 | F14: 54 | G14: =D14*Settings!$B$8/100 | H14: =D14*Settings!$B$9/100 | I14: =F14/Settings!$B$10/100 | J14: Record COVID-era earnings
A15: 44610 | B15: H1 FY2022 | C15: 90 | D15: 165 | E15: 37 | F15: 64 | G15: =D15*Settings!$B$8/100 | H15: =D15*Settings!$B$9/100 | I15: =F15/Settings!$B$10/100
A16: 44792 | B16: FY2022 | C16: 95.5 | D16: 178 | E16: 36 | F16: 68 | G16: =D16*Settings!$B$8/100 | H16: =D16*Settings!$B$9/100 | I16: =F16/Settings!$B$10/100 | J16: Peak post-COVID
A17: 44974 | B17: H1 FY2023 | C17: 66 | D17: 155 | E17: 28 | F17: 62 | G17: =D17*Settings!$B$8/100 | H17: =D17*Settings!$B$9/100 | I17: =F17/Settings!$B$10/100 | J17: Normalising
A18: 45156 | B18: FY2023 | C18: 53.5 | D18: 131 | E18: 26 | F18: 57 | G18: =D18*Settings!$B$8/100 | H18: =D18*Settings!$B$9/100 | I18: =F18/Settings!$B$10/100
A19: 45338 | B19: H1 FY2024 | C19: 58.5 | D19: 124 | E19: 26.5 | F19: 55 | G19: =D19*Settings!$B$8/100 | H19: =D19*Settings!$B$9/100 | I19: =F19/Settings!$B$10/100 | J19: FY2024 underlying EPS ~124.88c
A20: 45520 | B20: FY2024 | C20: 62.9 | D20: 124.88 | E20: 28.5 | F20: 56 | G20: =D20*Settings!$B$8/100 | H20: =D20*Settings!$B$9/100 | I20: =F20/Settings!$B$10/100 | J20: FY2024 confirmed EPS 124.88c
A21: 45709 | B21: H1 FY2025 | C21: 57.6 | D21: 120 | E21: 26 | F21: 54 | G21: =D21*Settings!$B$8/100 | H21: =D21*Settings!$B$9/100 | I21: =F21/Settings!$B$10/100 | J21: Est.
A22: 45891 | B22: FY2025 | C22: 58 | D22: 118 | E22: 26 | F22: 53 | G22: =D22*Settings!$B$8/100 | H22: =D22*Settings!$B$9/100 | I22: =F22/Settings!$B$10/100 | J22: Est.
A23: 46073 | B23: H1 FY2026 | C23: 57 | D23: 116 | E23: 25.5 | F23: 52 | G23: =D23*Settings!$B$8/100 | H23: =D23*Settings!$B$9/100 | I23: =F23/Settings!$B$10/100 | J23: Est. — H1 FY2026 NPAT ~$42.2M confirmed; update TTM when full data available
A25: TTM EPS = trailing 12-month underlying EPS | Value Buy = TTM EPS × 20× ÷ 100 | Value Sell = TTM EPS × 35× ÷ 100 | Div/RRoR = TTM Div ÷ RRoR ÷ 100 | Ordinary dividends only — specials excluded

Sheet PriceData
A1: ARB Corporation (ASX: ARB) — Weekly Price & Value Data
A2: Date (Fri) | B2: Price (AUD $) | C2: TTM EPS (¢) | D2: Value Buy (20× E) | E2: Value Sell (35× E) | F2: TTM Div (¢) | G2: Div / RRoR ($) | H2: P/E Ratio | I2: P/E 60D Avg
A3: 42370 | B3: 2.03
A4: 42377 | B4: 1.91
A5: 42384 | B5: 2.11
A6: 42391 | B6: 2.15
A7: 42398 | B7: 1.88
A8: 42405 | B8: 1.96
A9: 42412 | B9: 2.12
A10: 42419 | B10: 2.09 | C10: 55 | D10: 11 | E10: 19.25 | F10: 26 | G10: 8.6666667 | H10: 3.8
A11: 42426 | B11: 2.14 | C11: 55 | D11: 11 | E11: 19.25 | F11: 26 | G11: 8.6666667 | H11: 3.8909091
A12: 42433 | B12: 2.07 | C12: 55 | D12: 11 | E12: 19.25 | F12: 26 | G12: 8.6666667 | H12: 3.7636364
A13: 42440 | B13: 2.27 | C13: 55 | D13: 11 | E13: 19.25 | F13: 26 | G13: 8.6666667 | H13: 4.1272727 | I13: 3.9
A14: 42447 | B14: 2.27 | C14: 55 | D14: 11 | E14: 19.25 | F14: 26 | G14: 8.6666667 | H14: 4.1272727 | I14: 3.94
A15: 42454 | B15: 2.22 | C15: 55 | D15: 11 | E15: 19.25 | F15: 26 | G15: 8.6666667 | H15: 4.0363636 | I15: 3.96
A16: 42461 | B16: 2.34 | C16: 55 | D16: 11 | E16: 19.25 | F16: 26 | G16: 8.6666667 | H16: 4.2545455 | I16: 4
A17: 42468 | B17: 2.3 | C17: 55 | D17: 11 | E17: 19.25 | F17: 26 | G17: 8.6666667 | H17: 4.1818182 | I17: 4.02
A18: 42475 | B18: 2.18 | C18: 55 | D18: 11 | E18: 19.25 | F18: 26 | G18: 8.6666667 | H18: 3.9636364 | I18: 4.02
A19: 42482 | B19: 2.32 | C19: 55 | D19: 11 | E19: 19.25 | F19: 26 | G19: 8.6666667 | H19: 4.2181818 | I19: 4.04
A20: 42489 | B20: 2.21 | C20: 55 | D20: 11 | E20: 19.25 | F20: 26 | G20: 8.6666667 | H20: 4.0181818 | I20: 4.03
A21: 42496 | B21: 2.41 | C21: 55 | D21: 11 | E21: 19.25 | F21: 26 | G21: 8.6666667 | H21: 4.3818182 | I21: 4.06
A22: 42503 | B22: 2.33 | C22: 55 | D22: 11 | E22: 19.25 | F22: 26 | G22: 8.6666667 | H22: 4.2363636 | I22: 4.1
A23: 42510 | B23: 2.34 | C23: 55 | D23: 11 | E23: 19.25 | F23: 26 | G23: 8.6666667 | H23: 4.2545455 | I23: 4.13
A24: 42517 | B24: 2.3 | C24: 55 | D24: 11 | E24: 19.25 | F24: 26 | G24: 8.6666667 | H24: 4.1818182 | I24: 4.17
... A532: 46073 | B532: 2.17 | C532: 116 | D532: 23.2 | E532: 40.6 | F532: 52 | G532: 17.333333 | H532: 1.8706897 | I532: 1.84

Sheet ValueChart
A1: ARB Corporation (ASX: ARB) — Buy / Sell Zone Chart | Buy 20× (Slow to buy) | Sell 35× (Even slower to sell)
A2: RRoR 3% | P/E 60-day avg | Change in Settings sheet
A45: CHART INTERPRETATION
A46: SLOW TO BUY: Price (blue) < Value Buy (dark green dashed, 20× TTM EPS) → consider buying.
A47: EVEN SLOWER TO SELL: Price > Value Sell (red dashed, 35× TTM EPS) → only then consider trimming.
A48: P/E (olive, right axis, max 50.0×): context for whether earnings multiple is stretched.
A49: Div/RRoR (light green): price ≤ this line → dividend yield covers your return hurdle.

Sheet FuturePrompt
A1: FUTURE PROMPT — Copy this text to regenerate or adapt the spreadsheet for any ASX company
A2: '=== ASX VALUE CHART — AGENT PROMPT v3 ===
A3: To regenerate: run python scripts/build_value_chart.py ARB.AX
A4: To create new company: copy valuations/arb_ax.yaml,
A5: update all fields, then run python scripts/build_value_chart.py NEW.AX
A7: Reference template: outputs/NHC_ASX_Value_Analysis_v3.xlsx (cyclical example)
A8: Builder module: wally/value_chart_builder.py
A9: Config schema: valuations/nhc_ax.yaml (full annotated example)
A11: ━━━━ COMPANY ━━━━━━━━━━━━━━━━━━━━━━━━━━━━━━━━━━━━━━━━━━━━━━━━━━━━
A12: ticker: ARB.AX
A13: company_name: ARB Corporation
A14: business: 4WD accessories manufacturer & retailer — Aus domestic + export
... A122: Microsoft 365: =STOCKHISTORY("ARB.AX",DATE(2016,1,1),TODAY(),0,1,0,1)
